datafet/__init__.py
datafet/__init__.pyi
datafet/aws_operations.py
datafet/aws_operations.pyi
datafet/custom_types.py
datafet/custom_types.pyi
datafet/eid.py
datafet/eid.pyi
datafet/etl_helpers.py
datafet/etl_helpers.pyi
datafet/http_return.py
datafet/http_return.pyi
datafet/jwt_auth.py
datafet/jwt_auth.pyi
datafet/utility.py
datafet/utility.pyi
datafet/http/__init__.py
datafet/http/echo.py
datafet/http/echo.pyi
datafet/http/version.py
datafet/http/version.pyi
datafet-0.9.7.dist-info/WHEEL
datafet-0.9.7.dist-info/METADATA
datafet-0.9.7.dist-info/RECORD
